{
  "$schema": "https://mintlify.com/docs.json",
  "name": "Zeytin",
  "theme": "aspen",
  "colors": {
    "primary": "#28a7d9",
    "light": "#1b895b",
    "dark": "#f1c665"
  },
  "favicon": "https://media.brand.dev/9702bc4c-9eda-4291-97a4-c9d0eb6288f5.png",
  "navbar": {
    "primary": {
      "type": "github",
      "href": "https://github.com/berkaysahiin/Zeytin"
    }
  },
  "footer": {
    "socials": {
      "github": "https://github.com/berkaysahiin/Zeytin"
    }
  },
  "navigation": {
    "tabs": [
      {
        "tab": "Documentation",
        "groups": [
          {
            "group": "Get Started",
            "pages": [
              "introduction",
              "installation",
              "quickstart"
            ]
          },
          {
            "group": "The Editor",
            "pages": [
              "editor/overview",
              "editor/hierarchy",
              "editor/asset-browser",
              "editor/play-mode"
            ]
          },
          {
            "group": "Building Games",
            "pages": [
              "guides/variants",
              "guides/entities",
              "guides/levels",
              "guides/assets"
            ]
          },
          {
            "group": "Advanced",
            "pages": [
              "advanced/profiling",
              "advanced/testing",
              "advanced/preparser"
            ]
          }
        ]
      },
      {
        "tab": "API Reference",
        "groups": [
          {
            "group": "Core API",
            "pages": [
              "api/query",
              "api/component-lifecycle",
              "api/macros",
              "api/logging"
            ]
          },
          {
            "group": "Engine Internals",
            "pages": [
              "api/zeytin-class",
              "api/level-manager",
              "api/resource-manager"
            ]
          }
        ]
      }
    ]
  }
}
